{"nm":"tick","ddd":0,"h":32,"w":32,"meta":{"g":"@lottiefiles/toolkit-js 0.26.1"},"layers":[{"ty":4,"nm":"Tick","sr":1,"st":0,"op":66,"ip":0,"hd":false,"ddd":0,"bm":0,"hasMask":false,"ao":0,"ks":{"a":{"a":0,"k":[51.824,35.636,0],"ix":1},"s":{"a":0,"k":[16,16,100],"ix":6},"sk":{"a":0,"k":0},"p":{"a":0,"k":[13.97,13.75,0],"ix":2},"r":{"a":0,"k":0,"ix":10},"sa":{"a":0,"k":0},"o":{"a":0,"k":100,"ix":11}},"ef":[],"shapes":[{"ty":"gr","bm":0,"hd":false,"mn":"ADBE Vector Group","nm":"Group 1","ix":1,"cix":2,"np":2,"it":[{"ty":"sh","bm":0,"hd":false,"mn":"ADBE Vector Shape - Group","nm":"Path 1","ix":1,"d":1,"ks":{"a":0,"k":{"c":false,"i":[[0,0],[0,0],[0,0]],"o":[[0,0],[0,0],[0,0]],"v":[[0,0],[113.41,141.83],[206.26,47.12]]},"ix":2}},{"ty":"st","bm":0,"hd":false,"mn":"ADBE Vector Graphic - Stroke","nm":"Stroke 1","lc":2,"lj":2,"ml":1,"o":{"a":0,"k":100,"ix":4},"w":{"a":1,"k":[{"o":{"x":0.167,"y":0.167},"i":{"x":0.833,"y":0.833},"s":[23],"t":21},{"o":{"x":0.167,"y":0.167},"i":{"x":0.833,"y":0.833},"s":[49],"t":26},{"s":[22],"t":31.1533203125}],"ix":5},"c":{"a":0,"k":[0.3451,0.3608,0.898],"ix":3}},{"ty":"tr","a":{"a":0,"k":[0,0],"ix":1},"s":{"a":0,"k":[50.251,50.251],"ix":3},"sk":{"a":0,"k":0,"ix":4},"p":{"a":0,"k":[0,0],"ix":2},"r":{"a":0,"k":0,"ix":6},"sa":{"a":0,"k":0,"ix":5},"o":{"a":0,"k":100,"ix":7}}]},{"ty":"tm","bm":0,"hd":false,"mn":"ADBE Vector Filter - Trim","nm":"Trim Paths 1","ix":2,"e":{"a":1,"k":[{"o":{"x":0.333,"y":0},"i":{"x":0.833,"y":0.833},"s":[0],"t":19.731},{"o":{"x":0.333,"y":0},"i":{"x":0.833,"y":0.833},"s":[100],"t":32.424},{"s":[90],"t":34.9619140625}],"ix":2},"o":{"a":0,"k":0,"ix":3},"s":{"a":1,"k":[{"o":{"x":0.3,"y":0},"i":{"x":0.702,"y":0.838},"s":[0],"t":25.823},{"o":{"x":0.428,"y":-0.65},"i":{"x":0.784,"y":1},"s":[52.381],"t":31.917},{"s":[43],"t":34.9619140625}],"ix":1},"m":1}],"ind":1},{"ty":4,"nm":"Circle","sr":1,"st":0,"op":66,"ip":0,"hd":false,"ddd":0,"bm":0,"hasMask":false,"ao":0,"ks":{"a":{"a":0,"k":[0,0,0],"ix":1},"s":{"a":0,"k":[16,16,100],"ix":6},"sk":{"a":0,"k":0},"p":{"a":0,"k":[16,16,0],"ix":2},"r":{"a":0,"k":-52.499,"ix":10},"sa":{"a":0,"k":0},"o":{"a":0,"k":100,"ix":11}},"ef":[],"shapes":[{"ty":"gr","bm":0,"hd":false,"mn":"ADBE Vector Group","nm":"Circle","ix":1,"cix":2,"np":2,"it":[{"ty":"el","bm":0,"hd":false,"mn":"ADBE Vector Shape - Ellipse","nm":"Ellipse Path 1","d":1,"p":{"a":0,"k":[0,0],"ix":3},"s":{"a":0,"k":[336,336],"ix":2}},{"ty":"st","bm":0,"hd":false,"mn":"ADBE Vector Graphic - Stroke","nm":"Stroke 1","lc":2,"lj":1,"ml":4,"o":{"a":0,"k":100,"ix":4},"w":{"a":1,"k":[{"o":{"x":0.167,"y":0.167},"i":{"x":0.833,"y":0.833},"s":[13],"t":20.309},{"o":{"x":0.167,"y":0.167},"i":{"x":0.833,"y":0.833},"s":[38],"t":25.385},{"s":[18],"t":31.73046875}],"ix":5},"c":{"a":0,"k":[0.3451,0.3608,0.898],"ix":3}},{"ty":"tr","a":{"a":0,"k":[0,0],"ix":1},"s":{"a":0,"k":[50.251,50.251],"ix":3},"sk":{"a":0,"k":0,"ix":4},"p":{"a":0,"k":[0,0],"ix":2},"r":{"a":0,"k":0,"ix":6},"sa":{"a":0,"k":0,"ix":5},"o":{"a":0,"k":100,"ix":7}}]},{"ty":"tm","bm":0,"hd":false,"mn":"ADBE Vector Filter - Trim","nm":"Trim Paths 1","ix":2,"e":{"a":1,"k":[{"o":{"x":1,"y":0.064},"i":{"x":0.941,"y":0.955},"s":[0.9],"t":0},{"s":[100],"t":19.6162109375}],"ix":2},"o":{"a":0,"k":0,"ix":3},"s":{"a":1,"k":[{"o":{"x":0.302,"y":0},"i":{"x":0.713,"y":1},"s":[0],"t":0},{"o":{"x":0.425,"y":0},"i":{"x":0.777,"y":1},"s":[0],"t":15.692},{"s":[0],"t":21.576171875}],"ix":1},"m":1}],"ind":2}],"v":"5.1.16","fr":60,"op":60,"ip":0,"assets":[]}